Workbook

Sheet Summary
A1: AI Software Engineer - 2026 sprint plan
A2: 28 Sep 2026 -> 31 Dec 2026. Tick tasks in 'Daily Plan' column L (choose ☑). Every number on this page is a formula over the other sheets.
A3: How to use: only edit the blue/yellow cells - Done (☐/☑) in Daily Plan / Projects / Papers, Status in Projects, and Notes. Excel 365 users may convert the Done column to native checkboxes (Insert > Checkbox); the formulas count both.
A5: Overall progress
A6: Start date | B6: =MIN('Daily Plan'!$B$2:$B$168) -> 46293
A7: End date | B7: =MAX('Daily Plan'!$B$2:$B$168) -> 46387
A8: Study days | B8: =SUMPRODUCT(1/COUNTIF('Daily Plan'!$B$2:$B$168,'Daily Plan'!$B$2:$B$168)) -> 82
A9: Tasks planned | B9: =COUNTA('Daily Plan'!$G$2:$G$168) -> 167
A10: Tasks done | B10: =(COUNTIF('Daily Plan'!$L$2:$L$168,"☑")+COUNTIF('Daily Plan'!$L$2:$L$168,TRUE())) -> 0
A11: Tasks done (%) | B11: =IFERROR(B10/B9,0) -> 0
A12: Hours planned | B12: =SUM('Daily Plan'!$J$2:$J$168) -> 290
A13: Hours done | B13: =SUMIF('Daily Plan'!$L$2:$L$168,"☑",'Daily Plan'!$J$2:$J$168)+SUMIF('Daily Plan'!$L$2:$L$168,TRUE(),'Daily Plan'!$J$2:$J$168) -> 0
A14: Hours done (%) | B14: =IFERROR(B13/B12,0) -> 0
A15: Tasks scheduled up to today | B15: =COUNTIF('Daily Plan'!$B$2:$B$168,"<="&TODAY()) -> 3
A16: Ahead (+) / behind (-) in tasks | B16: =B10-B15 -> -3
A17: Projects done | B17: =(COUNTIF(Projects!$H$2:$H$13,"☑")+COUNTIF(Projects!$H$2:$H$13,TRUE())) -> 0
A18: Papers read | B18: =(COUNTIF(Papers!$N$2:$N$82,"☑")+COUNTIF(Papers!$N$2:$N$82,TRUE())) -> 0
A19: Assumptions: 3.5 h Mon-Fri, 4.0 h Sat, Sunday rest; 25 Dec is a 0-hour buffer. Source: plan design (tools/plan_data.py).
A21: Progress by phase
A22: Phase | B22: Code | C22: Tasks | D22: Done | E22: Done % | F22: Hours | G22: Hours done
A23: Phase 0 - ML/DL revision | B23: P0 | C23: =COUNTIF('Daily Plan'!$E$2:$E$168,B23) -> 8 | D23: =COUNTIFS('Daily Plan'!$E$2:$E$168,B23,'Daily Plan'!$L$2:$L$168,"☑")+COUNTIFS('Daily Plan'!$E$2:$E$168,B23,'Daily Plan'!$L$2:$L$168,TRUE()) -> 0 | E23: =IFERROR(D23/C23,0) -> 0 | F23: =SUMIF('Daily Plan'!$E$2:$E$168,B23,'Daily Plan'!$J$2:$J$168) -> 10.5 | G23: =SUMIFS('Daily Plan'!$J$2:$J$168,'Daily Plan'!$E$2:$E$168,B23,'Daily Plan'!$L$2:$L$168,"☑")+SUMIFS('Daily Plan'!$J$2:$J$168,'Daily Plan'!$E$2:$E$168,B23,'Daily Plan'!$L$2:$L$168,TRUE()) -> 0
A24: Phase 1 - Transformers | B24: P1 | C24: =COUNTIF('Daily Plan'!$E$2:$E$168,B24) -> 19 | D24: =COUNTIFS('Daily Plan'!$E$2:$E$168,B24,'Daily Plan'!$L$2:$L$168,"☑")+COUNTIFS('Daily Plan'!$E$2:$E$168,B24,'Daily Plan'!$L$2:$L$168,TRUE()) -> 0 | E24: =IFERROR(D24/C24,0) -> 0 | F24: =SUMIF('Daily Plan'!$E$2:$E$168,B24,'Daily Plan'!$J$2:$J$168) -> 34 | G24: =SUMIFS('Daily Plan'!$J$2:$J$168,'Daily Plan'!$E$2:$E$168,B24,'Daily Plan'!$L$2:$L$168,"☑")+SUMIFS('Daily Plan'!$J$2:$J$168,'Daily Plan'!$E$2:$E$168,B24,'Daily Plan'!$L$2:$L$168,TRUE()) -> 0
A25: Phase 2 - LLMs & language modeling | B25: P2 | C25: =COUNTIF('Daily Plan'!$E$2:$E$168,B25) -> 16 | D25: =COUNTIFS('Daily Plan'!$E$2:$E$168,B25,'Daily Plan'!$L$2:$L$168,"☑")+COUNTIFS('Daily Plan'!$E$2:$E$168,B25,'Daily Plan'!$L$2:$L$168,TRUE()) -> 0 | E25: =IFERROR(D25/C25,0) -> 0 | F25: =SUMIF('Daily Plan'!$E$2:$E$168,B25,'Daily Plan'!$J$2:$J$168) -> 30 | G25: =SUMIFS('Daily Plan'!$J$2:$J$168,'Daily Plan'!$E$2:$E$168,B25,'Daily Plan'!$L$2:$L$168,"☑")+SUMIFS('Daily Plan'!$J$2:$J$168,'Daily Plan'!$E$2:$E$168,B25,'Daily Plan'!$L$2:$L$168,TRUE()) -> 0
A26: Phase 3 - Embeddings & information retrieval | B26: P3 | C26: =COUNTIF('Daily Plan'!$E$2:$E$168,B26) -> 11 | D26: =COUNTIFS('Daily Plan'!$E$2:$E$168,B26,'Daily Plan'!$L$2:$L$168,"☑")+COUNTIFS('Daily Plan'!$E$2:$E$168,B26,'Daily Plan'!$L$2:$L$168,TRUE()) -> 0 | E26: =IFERROR(D26/C26,0) -> 0 | F26: =SUMIF('Daily Plan'!$E$2:$E$168,B26,'Daily Plan'!$J$2:$J$168) -> 19 | G26: =SUMIFS('Daily Plan'!$J$2:$J$168,'Daily Plan'!$E$2:$E$168,B26,'Daily Plan'!$L$2:$L$168,"☑")+SUMIFS('Daily Plan'!$J$2:$J$168,'Daily Plan'!$E$2:$E$168,B26,'Daily Plan'!$L$2:$L$168,TRUE()) -> 0
A27: Phase 4 - RAG | B27: P4 | C27: =COUNTIF('Daily Plan'!$E$2:$E$168,B27) -> 13 | D27: =COUNTIFS('Daily Plan'!$E$2:$E$168,B27,'Daily Plan'!$L$2:$L$168,"☑")+COUNTIFS('Daily Plan'!$E$2:$E$168,B27,'Daily Plan'!$L$2:$L$168,TRUE()) -> 0 | E27: =IFERROR(D27/C27,0) -> 0 | F27: =SUMIF('Daily Plan'!$E$2:$E$168,B27,'Daily Plan'!$J$2:$J$168) -> 20.5 | G27: =SUMIFS('Daily Plan'!$J$2:$J$168,'Daily Plan'!$E$2:$E$168,B27,'Daily Plan'!$L$2:$L$168,"☑")+SUMIFS('Daily Plan'!$J$2:$J$168,'Daily Plan'!$E$2:$E$168,B27,'Daily Plan'!$L$2:$L$168,TRUE()) -> 0
A28: Phase 5 - LLM evaluation | B28: P5 | C28: =COUNTIF('Daily Plan'!$E$2:$E$168,B28) -> 12 | D28: =COUNTIFS('Daily Plan'!$E$2:$E$168,B28,'Daily Plan'!$L$2:$L$168,"☑")+COUNTIFS('Daily Plan'!$E$2:$E$168,B28,'Daily Plan'!$L$2:$L$168,TRUE()) -> 0 | E28: =IFERROR(D28/C28,0) -> 0 | F28: =SUMIF('Daily Plan'!$E$2:$E$168,B28,'Daily Plan'!$J$2:$J$168) -> 20 | G28: =SUMIFS('Daily Plan'!$J$2:$J$168,'Daily Plan'!$E$2:$E$168,B28,'Daily Plan'!$L$2:$L$168,"☑")+SUMIFS('Daily Plan'!$J$2:$J$168,'Daily Plan'!$E$2:$E$168,B28,'Daily Plan'!$L$2:$L$168,TRUE()) -> 0
A29: Phase 6 - Fine-tuning & post-training | B29: P6 | C29: =COUNTIF('Daily Plan'!$E$2:$E$168,B29) -> 12 | D29: =COUNTIFS('Daily Plan'!$E$2:$E$168,B29,'Daily Plan'!$L$2:$L$168,"☑")+COUNTIFS('Daily Plan'!$E$2:$E$168,B29,'Daily Plan'!$L$2:$L$168,TRUE()) -> 0 | E29: =IFERROR(D29/C29,0) -> 0 | F29: =SUMIF('Daily Plan'!$E$2:$E$168,B29,'Daily Plan'!$J$2:$J$168) -> 22 | G29: =SUMIFS('Daily Plan'!$J$2:$J$168,'Daily Plan'!$E$2:$E$168,B29,'Daily Plan'!$L$2:$L$168,"☑")+SUMIFS('Daily Plan'!$J$2:$J$168,'Daily Plan'!$E$2:$E$168,B29,'Daily Plan'!$L$2:$L$168,TRUE()) -> 0
A30: Phase 7 - AI agents | B30: P7 | C30: =COUNTIF('Daily Plan'!$E$2:$E$168,B30) -> 11 | D30: =COUNTIFS('Daily Plan'!$E$2:$E$168,B30,'Daily Plan'!$L$2:$L$168,"☑")+COUNTIFS('Daily Plan'!$E$2:$E$168,B30,'Daily Plan'!$L$2:$L$168,TRUE()) -> 0 | E30: =IFERROR(D30/C30,0) -> 0 | F30: =SUMIF('Daily Plan'!$E$2:$E$168,B30,'Daily Plan'!$J$2:$J$168) -> 18 | G30: =SUMIFS('Daily Plan'!$J$2:$J$168,'Daily Plan'!$E$2:$E$168,B30,'Daily Plan'!$L$2:$L$168,"☑")+SUMIFS('Daily Plan'!$J$2:$J$168,'Daily Plan'!$E$2:$E$168,B30,'Daily Plan'!$L$2:$L$168,TRUE()) -> 0
A31: Phase 8 - MCP | B31: P8 | C31: =COUNTIF('Daily Plan'!$E$2:$E$168,B31) -> 2 | D31: =COUNTIFS('Daily Plan'!$E$2:$E$168,B31,'Daily Plan'!$L$2:$L$168,"☑")+COUNTIFS('Daily Plan'!$E$2:$E$168,B31,'Daily Plan'!$L$2:$L$168,TRUE()) -> 0 | E31: =IFERROR(D31/C31,0) -> 0 | F31: =SUMIF('Daily Plan'!$E$2:$E$168,B31,'Daily Plan'!$J$2:$J$168) -> 3.5 | G31: =SUMIFS('Daily Plan'!$J$2:$J$168,'Daily Plan'!$E$2:$E$168,B31,'Daily Plan'!$L$2:$L$168,"☑")+SUMIFS('Daily Plan'!$J$2:$J$168,'Daily Plan'!$E$2:$E$168,B31,'Daily Plan'!$L$2:$L$168,TRUE()) -> 0
A32: Phase 9 - Inference & GPU optimization | B32: P9 | C32: =COUNTIF('Daily Plan'!$E$2:$E$168,B32) -> 12 | D32: =COUNTIFS('Daily Plan'!$E$2:$E$168,B32,'Daily Plan'!$L$2:$L$168,"☑")+COUNTIFS('Daily Plan'!$E$2:$E$168,B32,'Daily Plan'!$L$2:$L$168,TRUE()) -> 0 | E32: =IFERROR(D32/C32,0) -> 0 | F32: =SUMIF('Daily Plan'!$E$2:$E$168,B32,'Daily Plan'!$J$2:$J$168) -> 19 | G32: =SUMIFS('Daily Plan'!$J$2:$J$168,'Daily Plan'!$E$2:$E$168,B32,'Daily Plan'!$L$2:$L$168,"☑")+SUMIFS('Daily Plan'!$J$2:$J$168,'Daily Plan'!$E$2:$E$168,B32,'Daily Plan'!$L$2:$L$168,TRUE()) -> 0
A33: Phase 10 - Multimodal AI | B33: P10 | C33: =COUNTIF('Daily Plan'!$E$2:$E$168,B33) -> 8 | D33: =COUNTIFS('Daily Plan'!$E$2:$E$168,B33,'Daily Plan'!$L$2:$L$168,"☑")+COUNTIFS('Daily Plan'!$E$2:$E$168,B33,'Daily Plan'!$L$2:$L$168,TRUE()) -> 0 | E33: =IFERROR(D33/C33,0) -> 0 | F33: =SUMIF('Daily Plan'!$E$2:$E$168,B33,'Daily Plan'!$J$2:$J$168) -> 14.5 | G33: =SUMIFS('Daily Plan'!$J$2:$J$168,'Daily Plan'!$E$2:$E$168,B33,'Daily Plan'!$L$2:$L$168,"☑")+SUMIFS('Daily Plan'!$J$2:$J$168,'Daily Plan'!$E$2:$E$168,B33,'Daily Plan'!$L$2:$L$168,TRUE()) -> 0
A34: Phase 11 - Advanced LLM training (distributed, data, scaling) | B34: P11 | C34: =COUNTIF('Daily Plan'!$E$2:$E$168,B34) -> 5 | D34: =COUNTIFS('Daily Plan'!$E$2:$E$168,B34,'Daily Plan'!$L$2:$L$168,"☑")+COUNTIFS('Daily Plan'!$E$2:$E$168,B34,'Daily Plan'!$L$2:$L$168,TRUE()) -> 0 | E34: =IFERROR(D34/C34,0) -> 0 | F34: =SUMIF('Daily Plan'!$E$2:$E$168,B34,'Daily Plan'!$J$2:$J$168) -> 8.5 | G34: =SUMIFS('Daily Plan'!$J$2:$J$168,'Daily Plan'!$E$2:$E$168,B34,'Daily Plan'!$L$2:$L$168,"☑")+SUMIFS('Daily Plan'!$J$2:$J$168,'Daily Plan'!$E$2:$E$168,B34,'Daily Plan'!$L$2:$L$168,TRUE()) -> 0
... A37: Capstone - AI Software Engineer | B37: CAP | C37: =COUNTIF('Daily Plan'!$E$2:$E$168,B37) -> 10 | D37: =COUNTIFS('Daily Plan'!$E$2:$E$168,B37,'Daily Plan'!$L$2:$L$168,"☑")+COUNTIFS('Daily Plan'!$E$2:$E$168,B37,'Daily Plan'!$L$2:$L$168,TRUE()) -> 0 | E37: =IFERROR(D37/C37,0) -> 0 | F37: =SUMIF('Daily Plan'!$E$2:$E$168,B37,'Daily Plan'!$J$2:$J$168) -> 27 | G37: =SUMIFS('Daily Plan'!$J$2:$J$168,'Daily Plan'!$E$2:$E$168,B37,'Daily Plan'!$L$2:$L$168,"☑")+SUMIFS('Daily Plan'!$J$2:$J$168,'Daily Plan'!$E$2:$E$168,B37,'Daily Plan'!$L$2:$L$168,TRUE()) -> 0
A39: Progress by week
A40: Week focus | B40: Week | C40: Starts | D40: Tasks | E40: Done | F40: Done % | G40: Hours
A41: Diagnostic revision -> attention from scratch | B41: W1 | C41: 46293 | D41: =COUNTIF('Daily Plan'!$D$2:$D$168,B41) -> 15 | E41: =COUNTIFS('Daily Plan'!$D$2:$D$168,B41,'Daily Plan'!$L$2:$L$168,"☑")+COUNTIFS('Daily Plan'!$D$2:$D$168,B41,'Daily Plan'!$L$2:$L$168,TRUE()) -> 0 | F41: =IFERROR(E41/D41,0) -> 0 | G41: =SUMIF('Daily Plan'!$D$2:$D$168,B41,'Daily Plan'!$J$2:$J$168) -> 21.5
A42: The modern Transformer block (Llama-style) + encoder-decoder | B42: W2 | C42: 46300 | D42: =COUNTIF('Daily Plan'!$D$2:$D$168,B42) -> 13 | E42: =COUNTIFS('Daily Plan'!$D$2:$D$168,B42,'Daily Plan'!$L$2:$L$168,"☑")+COUNTIFS('Daily Plan'!$D$2:$D$168,B42,'Daily Plan'!$L$2:$L$168,TRUE()) -> 0 | F42: =IFERROR(E42/D42,0) -> 0 | G42: =SUMIF('Daily Plan'!$D$2:$D$168,B42,'Daily Plan'!$J$2:$J$168) -> 21.5
A43: Tokenization + training a small GPT (CS336 Assignment 1) | B43: W3 | C43: 46307 | D43: =COUNTIF('Daily Plan'!$D$2:$D$168,B43) -> 11 | E43: =COUNTIFS('Daily Plan'!$D$2:$D$168,B43,'Daily Plan'!$L$2:$L$168,"☑")+COUNTIFS('Daily Plan'!$D$2:$D$168,B43,'Daily Plan'!$L$2:$L$168,TRUE()) -> 0 | F43: =IFERROR(E43/D43,0) -> 0 | G43: =SUMIF('Daily Plan'!$D$2:$D$168,B43,'Daily Plan'!$J$2:$J$168) -> 21.5
A44: Inside inference: KV cache, sampling, scaling laws, MoE | B44: W4 | C44: 46314 | D44: =COUNTIF('Daily Plan'!$D$2:$D$168,B44) -> 13 | E44: =COUNTIFS('Daily Plan'!$D$2:$D$168,B44,'Daily Plan'!$L$2:$L$168,"☑")+COUNTIFS('Daily Plan'!$D$2:$D$168,B44,'Daily Plan'!$L$2:$L$168,TRUE()) -> 0 | F44: =IFERROR(E44/D44,0) -> 0 | G44: =SUMIF('Daily Plan'!$D$2:$D$168,B44,'Daily Plan'!$J$2:$J$168) -> 21.5
A45: Embeddings, contrastive learning and vector search internals | B45: W5 | C45: 46321 | D45: =COUNTIF('Daily Plan'!$D$2:$D$168,B45) -> 12 | E45: =COUNTIFS('Daily Plan'!$D$2:$D$168,B45,'Daily Plan'!$L$2:$L$168,"☑")+COUNTIFS('Daily Plan'!$D$2:$D$168,B45,'Daily Plan'!$L$2:$L$168,TRUE()) -> 0 | F45: =IFERROR(E45/D45,0) -> 0 | G45: =SUMIF('Daily Plan'!$D$2:$D$168,B45,'Daily Plan'!$J$2:$J$168) -> 21.5
A46: RAG: beginner -> advanced -> research level | B46: W6 | C46: 46328 | D46: =COUNTIF('Daily Plan'!$D$2:$D$168,B46) -> 14 | E46: =COUNTIFS('Daily Plan'!$D$2:$D$168,B46,'Daily Plan'!$L$2:$L$168,"☑")+COUNTIFS('Daily Plan'!$D$2:$D$168,B46,'Daily Plan'!$L$2:$L$168,TRUE()) -> 0 | F46: =IFERROR(E46/D46,0) -> 0 | G46: =SUMIF('Daily Plan'!$D$2:$D$168,B46,'Daily Plan'!$J$2:$J$168) -> 21.5
A47: Evaluation like a professional AI team | B47: W7 | C47: 46335 | D47: =COUNTIF('Daily Plan'!$D$2:$D$168,B47) -> 13 | E47: =COUNTIFS('Daily Plan'!$D$2:$D$168,B47,'Daily Plan'!$L$2:$L$168,"☑")+COUNTIFS('Daily Plan'!$D$2:$D$168,B47,'Daily Plan'!$L$2:$L$168,TRUE()) -> 0 | F47: =IFERROR(E47/D47,0) -> 0 | G47: =SUMIF('Daily Plan'!$D$2:$D$168,B47,'Daily Plan'!$J$2:$J$168) -> 21.5
A48: Fine-tuning: SFT, chat templates, LoRA and QLoRA | B48: W8 | C48: 46342 | D48: =COUNTIF('Daily Plan'!$D$2:$D$168,B48) -> 11 | E48: =COUNTIFS('Daily Plan'!$D$2:$D$168,B48,'Daily Plan'!$L$2:$L$168,"☑")+COUNTIFS('Daily Plan'!$D$2:$D$168,B48,'Daily Plan'!$L$2:$L$168,TRUE()) -> 0 | F48: =IFERROR(E48/D48,0) -> 0 | G48: =SUMIF('Daily Plan'!$D$2:$D$168,B48,'Daily Plan'!$J$2:$J$168) -> 21.5
A49: RL for LLMs: RLHF, DPO, RLVR/GRPO and reasoning models | B49: W9 | C49: 46349 | D49: =COUNTIF('Daily Plan'!$D$2:$D$168,B49) -> 13 | E49: =COUNTIFS('Daily Plan'!$D$2:$D$168,B49,'Daily Plan'!$L$2:$L$168,"☑")+COUNTIFS('Daily Plan'!$D$2:$D$168,B49,'Daily Plan'!$L$2:$L$168,TRUE()) -> 0 | F49: =IFERROR(E49/D49,0) -> 0 | G49: =SUMIF('Daily Plan'!$D$2:$D$168,B49,'Daily Plan'!$J$2:$J$168) -> 21.5
A50: Agents from first principles + MCP | B50: W10 | C50: 46356 | D50: =COUNTIF('Daily Plan'!$D$2:$D$168,B50) -> 13 | E50: =COUNTIFS('Daily Plan'!$D$2:$D$168,B50,'Daily Plan'!$L$2:$L$168,"☑")+COUNTIFS('Daily Plan'!$D$2:$D$168,B50,'Daily Plan'!$L$2:$L$168,TRUE()) -> 0 | F50: =IFERROR(E50/D50,0) -> 0 | G50: =SUMIF('Daily Plan'!$D$2:$D$168,B50,'Daily Plan'!$J$2:$J$168) -> 21.5
A51: GPUs and LLM inference optimization | B51: W11 | C51: 46363 | D51: =COUNTIF('Daily Plan'!$D$2:$D$168,B51) -> 14 | E51: =COUNTIFS('Daily Plan'!$D$2:$D$168,B51,'Daily Plan'!$L$2:$L$168,"☑")+COUNTIFS('Daily Plan'!$D$2:$D$168,B51,'Daily Plan'!$L$2:$L$168,TRUE()) -> 0 | F51: =IFERROR(E51/D51,0) -> 0 | G51: =SUMIF('Daily Plan'!$D$2:$D$168,B51,'Daily Plan'!$J$2:$J$168) -> 21.5
A52: Distributed training & data (working knowledge) + multimodal AI | B52: W12 | C52: 46370 | D52: =COUNTIF('Daily Plan'!$D$2:$D$168,B52) -> 12 | E52: =COUNTIFS('Daily Plan'!$D$2:$D$168,B52,'Daily Plan'!$L$2:$L$168,"☑")+COUNTIFS('Daily Plan'!$D$2:$D$168,B52,'Daily Plan'!$L$2:$L$168,TRUE()) -> 0 | F52: =IFERROR(E52/D52,0) -> 0 | G52: =SUMIF('Daily Plan'!$D$2:$D$168,B52,'Daily Plan'!$J$2:$J$168) -> 21.5
... A54: Capstone hardening, final assessment, 2027 plan | B54: W14 | C54: 46384 | D54: =COUNTIF('Daily Plan'!$D$2:$D$168,B54) -> 6 | E54: =COUNTIFS('Daily Plan'!$D$2:$D$168,B54,'Daily Plan'!$L$2:$L$168,"☑")+COUNTIFS('Daily Plan'!$D$2:$D$168,B54,'Daily Plan'!$L$2:$L$168,TRUE()) -> 0 | F54: =IFERROR(E54/D54,0) -> 0 | G54: =SUMIF('Daily Plan'!$D$2:$D$168,B54,'Daily Plan'!$J$2:$J$168) -> 14
A56: What you already know (skip or quick revision only)
A57: Topic | B57: Action in this plan
A58: Software engineering (design, testing, code review) | B58: Skip
A59: Backend / API development (FastAPI, REST, async) | B59: Skip
A60: Cloud, infrastructure, DevOps | B60: Skip
A61: Docker / Kubernetes | B61: Skip - used for sandboxes & serving only
A62: Databases (Postgres etc.) | B62: Skip - pgvector is the only new part
A63: CI/CD | B63: Skip - reused for eval regression gates
A64: Python (advanced) | B64: Skip
A65: PyTorch working knowledge | B65: Revise - einops, profiler, autograd internals (W1)
A66: Probability & statistics basics | B66: Revise - MLE -> cross-entropy, bootstrap CIs (W1, W7)
A67: Linear algebra | B67: Revise - matrix calculus for backprop, low-rank (W1, W8)
A68: Optimization (SGD, Adam) | B68: Revise - implement AdamW + schedules (W1, W3)
... A73: Neural networks / CNN basics | B73: Revise - CNN only as contrast for ViT (W12)
A75: What you are learning (target level) and deferred items
A76: MASTER = implement + explain without notes; WORKING = explain + use a library + one experiment; DEFER-2027 = scheduled in the 2027 continuation plan.
A77: Topic | B77: Phase | C77: Target level | D77: When | E77: Self-rating (1-5)
A78: Q/K/V, scaled dot-product, self/cross/causal attention, masking, MHA | B78: P1 | C78: MASTER | D78: W1
A79: Embeddings, positional encoding, residuals, LayerNorm vs RMSNorm | B79: P1 | C79: MASTER | D79: W2
A80: FFN vs SwiGLU, RoPE, GQA/MQA | B80: P1 | C80: MASTER | D80: W2
A81: Encoder vs decoder vs encoder-decoder; decoder-only LLMs | B81: P1 | C81: MASTER | D81: W2
A82: Mixture of Experts (routing, load balancing) | B82: P1 | C82: WORKING | D82: W4
A83: Tokenization: BPE, byte-level BPE, SentencePiece/unigram, vocab trade-offs | B83: P2 | C83: MASTER | D83: W3
A84: Next-token prediction, cross-entropy, teacher forcing, perplexity | B84: P2 | C84: MASTER | D84: W3
A85: Training dynamics: AdamW, warmup + cosine, clipping, instability | B85: P2 | C85: MASTER | D85: W3
A86: KV cache, prefill vs decode, context windows | B86: P2 | C86: MASTER | D86: W4
A87: Sampling: temperature, top-k, top-p, min-p, beam search, logits | B87: P2 | C87: MASTER | D87: W4
A88: Scaling laws, Chinchilla, model/data/compute trade-offs | B88: P2/P11 | C88: WORKING | D88: W4
A89: Embeddings, cosine similarity, contrastive learning (InfoNCE) | B89: P3 | C89: MASTER | D89: W5
... A139: LangGraph deployment / durable agents in production; other frameworks only if a job needs them | B139: P7 | C139: DEFER-2027 | D139: Q1 2027
A141: Example: rate 'KV cache, prefill vs decode' as 4 once you can derive the memory formula close-book.

Sheet Daily Plan
A1: # | B1: Date | C1: Day | D1: Week | E1: Phase | F1: Type | G1: Topic | H1: Description | I1: Link | J1: Hours | K1: Deliverable / assignment | L1: Done | M1: Notes
A2: 1 | B2: 46293 | C2: Mon | D2: W1 | E2: P0 | F2: Setup | G2: Workspace + GPU plan | H2: Create one monorepo for all 2026 projects (uv, pytest, ruff, wandb or tensorboard). Decide compute: Mac/Colab for small runs, rented A10/L4/4090 by the hour for training weeks. | I2: https://pytorch.org/get-started/locally/ | J2: 0.5 | K2: Repo skeleton | L2: ☐
A3: 2 | B3: 46293 | C3: Mon | D3: W1 | E3: P0 | F3: Review | G3: Diagnostic self-test | H3: Take the Phase 0 self-test in the checkpoints file. Anything you answer confidently in <2 min is skipped this week. | I3: https://github.com/anshu8830/anshu/blob/main/curriculum/08-skill-checkpoints.md | J3: 1 | K3: List of gaps | L3: ☐
A4: 3 | B4: 46293 | C4: Mon | D4: W1 | E4: P0 | F4: Reading | G4: Probability -> MLE -> cross-entropy; optimizers | H4: UDL ch. 5 (loss functions as MLE) and ch. 6 (SGD, momentum, Adam). Then implement AdamW from scratch and match PyTorch. | I4: https://udlbook.github.io/udlbook/ | J4: 2 | K4: adamw.py + test | L4: ☐
A5: 4 | B5: 46294 | C5: Tue | D5: W1 | E5: P0 | F5: Video | G5: Backprop by hand | H5: Backprop Ninja (skip if diagnostic passed). Exercise: manual backward for Linear->LayerNorm->GELU->Linear->softmax-CE; verify with torch.autograd.gradcheck. | I5: https://www.youtube.com/watch?v=q8SA3rM6ckI | J5: 2 | K5: manual_backward.py | L5: ☐
A6: 5 | B6: 46294 | C6: Tue | D6: W1 | E6: P0 | F6: Reading | G6: Matrix calculus refresh | H6: Parr & Howard sections on vector chain rule + UDL ch. 7. Derive dL/dlogits = softmax - onehot and the LayerNorm backward on paper. | I6: https://explained.ai/matrix-calculus/ | J6: 1.5 | K6: 1-page derivation | L6: ☐
A7: 6 | B7: 46295 | C7: Wed | D7: W1 | E7: P0 | F7: Video | G7: PyTorch + resource accounting | H7: CS336 L2 (trace + video in 2026 playlist): tensors, einops, FLOPs and memory accounting. Exercise: FLOPs of a (B,T,d)x(d,4d) matmul; memory of a 1B model in fp32/bf16 incl. Adam states. | I7: https://cs336.stanford.edu/lectures/?trace=lecture_02 | J7: 1.5 | K7: accounting.md | L7: ☐
A8: 7 | B8: 46295 | C8: Wed | D8: W1 | E8: P0 | F8: Reading | G8: Generalization revision | H8: UDL ch. 8-9: bias/variance, double descent, weight decay, dropout, early stopping. 1 hour max. | I8: https://udlbook.github.io/udlbook/ | J8: 1 | L8: ☐
A9: 8 | B9: 46295 | C9: Wed | D9: W1 | E9: P0 | F9: Code | G9: Evaluation revision | H9: Implement precision/recall/F1, ROC-AUC vs PR-AUC and expected calibration error (ECE) on a toy classifier. | I9: https://udlbook.github.io/udlbook/ | J9: 1 | K9: metrics.py | L9: ☐
A10: 9 | B10: 46296 | C10: Thu | D10: W1 | E10: P1 | F10: Video | G10: Attention intuition | H10: 3Blue1Brown DL5 + DL6 back to back. | I10: https://www.youtube.com/watch?v=eMlx5fFNoYc | J10: 1 | L10: ☐
A11: 10 | B11: 46296 | C11: Thu | D11: W1 | E11: P1 | F11: Reading | G11: Illustrated Transformer | H11: Read end-to-end; sketch the encoder/decoder data flow yourself. | I11: https://jalammar.github.io/illustrated-transformer/ | J11: 1 | K11: Hand-drawn diagram | L11: ☐
A12: 11 | B12: 46296 | C12: Thu | D12: W1 | E12: P13 | F12: Paper | G12: Attention Is All You Need (3-pass) | H12: Read Keshav (15 min), then the paper: 3.1-3.2.3, 3.5, Table 3. Write notes with tensor shapes. | I12: https://arxiv.org/abs/1706.03762 | J12: 1.5 | K12: Paper notes #1 | L12: ☐
A13: 12 | B13: 46297 | C13: Fri | D13: W1 | E13: P1 | F13: Reading | G13: Math -> tensor shapes | H13: Work through the attention concept note; fill every shape in the table yourself before reading the answer. | I13: https://github.com/anshu8830/anshu/blob/main/curriculum/concepts/01-attention-and-transformer.md | J13: 1 | L13: ☐
A14: 13 | B14: 46297 | C14: Fri | D14: W1 | E14: P1 | F14: Code | G14: Scaled dot-product attention | H14: Implement SDPA with causal + padding masks. Tests: equals F.scaled_dot_product_attention (atol 1e-6); perturbing future tokens does not change past outputs. | I14: https://github.com/anshu8830/anshu/blob/main/curriculum/concepts/01-attention-and-transformer.md | J14: 2.5 | K14: P1: sdpa + tests | L14: ☐
A15: 14 | B15: 46298 | C15: Sat | D15: W1 | E15: P1 | F15: Code | G15: Multi-head + cross attention | H15: Fused QKV projection, split heads with view/transpose (or einops), output projection; cross-attention variant. Test against nn.MultiheadAttention with copied weights. | I15: https://nlp.seas.harvard.edu/annotated-transformer/ | J15: 2.5 | K15: P1: mha.py | L15: ☐
A16: 15 | B16: 46298 | C16: Sat | D16: W1 | E16: P1 | F16: Experiment | G16: Attention experiments | H16: (a) remove 1/sqrt(d_k): plot softmax entropy vs d_k; (b) visualize attention maps on a toy sequence; (c) measure attention-matrix memory vs T. | I16: https://github.com/anshu8830/anshu/blob/main/curriculum/concepts/01-attention-and-transformer.md | J16: 1.5 | K16: P1 notebook (DONE) | L16: ☐
A17: 16 | B17: 46300 | C17: Mon | D17: W2 | E17: P1 | F17: Video | G17: Let's build GPT (code along) | H17: Watch at 1.25x and type the code; stop at each stage and predict the next change before Karpathy makes it. | I17: https://www.youtube.com/watch?v=kCc8FmEb1nY | J17: 2.5 | K17: gpt_karpathy.py | L17: ☐
A18: 17 | B18: 46300 | C18: Mon | D18: W2 | E18: P1 | F18: Reading | G18: Annotated Transformer skim | H18: Skim the encoder-decoder parts you will need on Saturday. | I18: https://nlp.seas.harvard.edu/annotated-transformer/ | J18: 1 | L18: ☐
A19: 18 | B19: 46301 | C19: Tue | D19: W2 | E19: P1 | F19: Video | G19: CS336 L3 - Architectures | H19: Video + slides: pre vs post norm, RMSNorm, SwiGLU, RoPE, parallel layers, d_ff = 8/3 d, head dim conventions. | I19: https://www.youtube.com/watch?v=lVynu4bo1rY | J19: 1.5 | K19: Notes | L19: ☐
A20: 19 | B20: 46301 | C20: Tue | D20: W2 | E20: P1 | F20: Reading | G20: Big LLM Architecture Comparison | H20: Read the Llama, Qwen, DeepSeek (MLA/MoE) and gpt-oss sections. | I20: https://magazine.sebastianraschka.com/p/the-big-llm-architecture-comparison | J20: 1 | L20: ☐
A21: 20 | B21: 46301 | C21: Tue | D21: W2 | E21: P13 | F21: Paper | G21: Pre-LN, RMSNorm, GLU variants | H21: Short reads: Pre-LN sec. 1+3 (skip proofs), RMSNorm sec. 3, GLU Variants (whole). | I21: https://arxiv.org/abs/2002.04745 | J21: 1 | K21: Paper notes #2 | L21: ☐
A22: 21 | B22: 46302 | C22: Wed | D22: W2 | E22: P1 | F22: Code | G22: Block components | H22: Embeddings + (learned/sinusoidal) PE, LayerNorm & RMSNorm, FFN vs SwiGLU, pre-norm residual block, weight tying. Parameter-count function tested against ~12*L*d^2 + embeddings. | I22: https://github.com/anshu8830/anshu/blob/main/curriculum/concepts/01-attention-and-transformer.md | J22: 3.5 | K22: P2: components + tests | L22: ☐
A23: 22 | B23: 46303 | C23: Thu | D23: W2 | E23: P1 | F23: Video | G23: RoPE / GQA explained | H23: Umar Jamil LLaMA explained - RoPE, RMSNorm, GQA, SwiGLU sections. | I23: https://www.youtube.com/watch?v=Mn_9W1nCFLo | J23: 1 | L23: ☐
A24: 23 | B24: 46303 | C24: Thu | D24: W2 | E24: P13 | F24: Paper | G24: RoFormer | H24: Sections 3.1-3.4. | I24: https://arxiv.org/abs/2104.09864 | J24: 0.5 | L24: ☐
A25: 24 | B25: 46303 | C25: Thu | D25: W2 | E25: P1 | F25: Code | G25: Implement RoPE | H25: Rotation form; test that <RoPE(q,m), RoPE(k,n)> depends only on m-n; compare interleaved (GPT-J) vs half-split (GPT-NeoX/Llama HF) layouts. | I25: https://github.com/anshu8830/anshu/blob/main/curriculum/concepts/01-attention-and-transformer.md | J25: 2 | K25: P2: rope.py + test | L25: ☐
A26: 25 | B26: 46304 | C26: Fri | D26: W2 | E26: P13 | F26: Paper | G26: MQA + GQA | H26: MQA sec. 2-3, GQA sec. 2-3. Compute KV-cache bytes for a Llama-3-8B-like config under MHA/GQA/MQA. | I26: https://arxiv.org/abs/2305.13245 | J26: 1 | K26: KV math table | L26: ☐
A27: 26 | B27: 46304 | C27: Fri | D27: W2 | E27: P1 | F27: Code | G27: GQA + assemble GPT | H27: GQA via repeat_interleave; flags for MHA/MQA. Assemble decoder-only GPT (dataclass config). Tests: causal leakage, shapes, param count. | I27: https://github.com/anshu8830/anshu/blob/main/curriculum/concepts/01-attention-and-transformer.md | J27: 2.5 | K27: P2: model.py | L27: ☐
A28: 27 | B28: 46305 | C28: Sat | D28: W2 | E28: P1 | F28: Project | G28: Encoder-decoder Transformer | H28: Bidirectional encoder + decoder with cross-attention; train on sequence reversal or 3-digit addition until >99% exact match. | I28: https://nlp.seas.harvard.edu/annotated-transformer/ | J28: 3 | K28: P2: seq2seq.py | L28: ☐
A29: 28 | B29: 46305 | C29: Sat | D29: W2 | E29: P1 | F29: Review | G29: Encoder vs decoder write-up | H29: BERT sec. 3 skim (15 min). Write 1 page: encoder-only vs decoder-only vs enc-dec, and why decoder-only dominates LLMs. | I29: https://arxiv.org/abs/1810.04805 | J29: 1 | K29: P2 README (DONE) | L29: ☐
A30: 29 | B30: 46307 | C30: Mon | D30: W3 | E30: P2 | F30: Video | G30: Let's build the GPT Tokenizer | H30: Watch with minbpe open; pause to implement get_stats/merge yourself. | I30: https://www.youtube.com/watch?v=zduSFxRajkE | J30: 2.5 | L30: ☐
A31: 30 | B31: 46307 | C31: Mon | D31: W3 | E31: P13 | F31: Paper | G31: BPE (Sennrich) + GPT-2 input representation | H31: BPE sec. 3.2 + Algorithm 1; GPT-2 sec. 2.2. | I31: https://arxiv.org/abs/1508.07909 | J31: 1 | K31: Paper notes #3 | L31: ☐
A32: 31 | B32: 46308 | C32: Tue | D32: W3 | E32: P2 | F32: Video | G32: CS336 L1 - Overview & tokenization | H32: Video + A1 handout BPE section. | I32: https://www.youtube.com/watch?v=JuoVZkPBiKk | J32: 1.5 | L32: ☐
A33: 32 | B33: 46308 | C33: Tue | D33: W3 | E33: P2 | F33: Code | G33: BPE trainer v1 | H33: Naive byte-level BPE trainer with GPT-2 pre-tokenization regex and special tokens. | I33: https://github.com/stanford-cs336/assignment1-basics | J33: 2 | K33: P3: bpe_train.py | L33: ☐
A34: 33 | B34: 46309 | C34: Wed | D34: W3 | E34: P2 | F34: Code | G34: BPE trainer v2 + tokenizer | H34: Incremental pair-count updates, parallel pre-tokenization on chunk boundaries; 10K vocab on TinyStories; encode/decode; run A1 tokenizer tests. | I34: https://github.com/stanford-cs336/assignment1-basics | J34: 2 | K34: P3: tokenizer passes A1 tests | L34: ☐
A35: 34 | B35: 46309 | C35: Wed | D35: W3 | E35: P2 | F35: Experiment | G35: SentencePiece vs BPE | H35: Read SentencePiece sec. 2-3; train BPE vs unigram on same text; compare bytes/token and vocab-size trade-off (embedding params vs sequence length). | I35: https://arxiv.org/abs/1808.06226 | J35: 1.5 | K35: Comparison table | L35: ☐
A36: 35 | B36: 46310 | C36: Thu | D36: W3 | E36: P2 | F36: Reading | G36: LM objective math | H36: Concept note: next-token prediction, cross-entropy = NLL, teacher forcing, perplexity, bits-per-byte. | I36: https://github.com/anshu8830/anshu/blob/main/curriculum/concepts/02-prompt-to-next-token.md | J36: 1 | L36: ☐
A37: 36 | B37: 46310 | C37: Thu | D37: W3 | E37: P2 | F37: Code | G37: Training loop (A1 components) | H37: memmap token dataset, random batch sampler, own AdamW, warmup + cosine LR, grad clipping, checkpoint save/load; pass the A1 tests for each. | I37: https://github.com/stanford-cs336/assignment1-basics | J37: 2.5 | K37: P3: train.py | L37: ☐
A38: 37 | B38: 46311 | C38: Fri | D38: W3 | E38: P2 | F38: Experiment | G38: Train on TinyStories | H38: ~20-30M params on one rented GPU (or smaller on MPS). Log train/val loss, tokens/s, estimated MFU. Aim for the A1 handout's TinyStories target. | I38: https://github.com/stanford-cs336/assignment1-basics | J38: 3.5 | K38: Loss curves | L38: ☐
A39: 38 | B39: 46312 | C39: Sat | D39: W3 | E39: P2 | F39: Code | G39: Generation + sampling | H39: Temperature, top-k, top-p sampling; generate 20 stories; read them critically. | I39: https://arxiv.org/abs/1904.09751 | J39: 2 | K39: generate.py | L39: ☐
A40: 39 | B40: 46312 | C40: Sat | D40: W3 | E40: P13 | F40: Experiment | G40: Reproduction #1 - architecture ablations | H40: RoPE vs NoPE vs learned absolute; pre-norm vs post-norm at high LR (Pre-LN paper claim); 3-point LR sweep. Plot and explain. | I40: https://arxiv.org/abs/2002.04745 | J40: 2 | K40: Ablation report | L40: ☐
A41: 40 | B41: 46314 | C41: Mon | D41: W4 | E41: P2 | F41: Reading | G41: Prompt -> next token walkthrough | H41: Read the concept note, then step through Bycroft's 3D visualization for one token. | I41: https://github.com/anshu8830/anshu/blob/main/curriculum/concepts/02-prompt-to-next-token.md | J41: 1 | L41: ☐
A42: 41 | B42: 46314 | C42: Mon | D42: W4 | E42: P2 | F42: Code | G42: KV cache | H42: Pre-allocated K/V tensors per layer, RoPE offsets, prefill vs decode code paths; measure ms/token with vs without cache as T grows. | I42: https://github.com/anshu8830/anshu/blob/main/curriculum/concepts/02-prompt-to-next-token.md | J42: 2.5 | K42: P3: kv_cache.py + plot | L42: ☐
A43: 42 | B43: 46315 | C43: Tue | D43: W4 | E43: P13 | F43: Paper | G43: Neural text degeneration | H43: Holtzman et al. sec. 3-5 (why greedy/beam degenerate; nucleus sampling). | I43: https://arxiv.org/abs/1904.09751 | J43: 1 | K43: Paper notes #4 | L43: ☐
A44: 43 | B44: 46315 | C44: Tue | D44: W4 | E44: P2 | F44: Code | G44: Sampling suite | H44: Beam search, top-p, min-p, repetition penalty; experiment distinct-n vs perplexity across settings; sliding-window perplexity eval. | I44: https://arxiv.org/abs/1904.09751 | J44: 2.5 | K44: P3: sampling study | L44: ☐
A45: 44 | B45: 46316 | C45: Wed | D45: W4 | E45: P2 | F45: Video | G45: CS336 L10 - Inference | H45: Trace + video: prefill/decode, arithmetic intensity, KV cache, batching. | I45: https://cs336.stanford.edu/lectures/?trace=lecture_10 | J45: 1.5 | L45: ☐
A46: 45 | B46: 46316 | C46: Wed | D46: W4 | E46: P2 | F46: Reading | G46: Transformer inference arithmetic | H46: kipply's post; redo its numbers for a model you care about. | I46: https://kipply.github.io/blog/transformer-inference-arithmetic/ | J46: 1 | L46: ☐
A47: 46 | B47: 46316 | C47: Wed | D47: W4 | E47: P2 | F47: Review | G47: Inference math exercises | H47: FLOPs/token ~ 2N; KV bytes/token = 2*L*n_kv*d_head*bytes; decode lower bound = bytes moved / bandwidth. Why long context is expensive (memory + positional extrapolation). | I47: https://github.com/anshu8830/anshu/blob/main/curriculum/concepts/02-prompt-to-next-token.md | J47: 1 | K47: inference_math.md | L47: ☐
A48: 47 | B48: 46317 | C48: Thu | D48: W4 | E48: P11 | F48: Reading | G48: Scaling laws | H48: CS336 L9 slides + video; Kaplan sec. 1-3 figures; Chinchilla sec. 3 (IsoFLOP approaches). | I48: https://arxiv.org/abs/2203.15556 | J48: 1.5 | K48: Paper notes #5 | L48: ☐
A49: 48 | B49: 46317 | C49: Thu | D49: W4 | E49: P13 | F49: Experiment | G49: Reproduction #2 - mini IsoFLOP | H49: 3 compute budgets x 4 model sizes on TinyStories (short runs in the background). Fit N_opt vs C and compare the exponent with Chinchilla (~0.5). Use C ~ 6ND. | I49: https://arxiv.org/abs/2203.15556 | J49: 2 | K49: isoflop.ipynb | L49: ☐
A50: 49 | B50: 46318 | C50: Fri | D50: W4 | E50: P1 | F50: Reading | G50: Mixture of Experts | H50: CS336 L4 slides/video + Grootendorst visual guide; Switch sec. 2.1-2.2; Mixtral sec. 2. | I50: https://newsletter.maartengrootendorst.com/p/a-visual-guide-to-mixture-of-experts | J50: 1.5 | L50: ☐
A51: 50 | B51: 46318 | C51: Fri | D51: W4 | E51: P1 | F51: Code | G51: MoE layer | H51: Token-choice top-k router, experts as SwiGLU FFNs, load-balancing auxiliary loss; swap into GPT. | I51: https://arxiv.org/abs/2101.03961 | J51: 2 | K51: moe.py | L51: ☐
A52: 51 | B52: 46319 | C52: Sat | D52: W4 | E52: P1 | F52: Experiment | G52: Dense vs MoE | H52: 8 experts top-2 vs dense at matched active params and tokens: loss, tokens/s, expert-utilization histogram. | I52: https://arxiv.org/abs/2101.03961 | J52: 2 | K52: MoE report | L52: ☐
A53: 52 | B53: 46319 | C53: Sat | D53: W4 | E53: P2 | F53: Review | G53: Phase 1-2 checkpoint | H53: Close-book: write 'prompt -> next token' with your own diagram and numbers; answer the Phase 1 and 2 checkpoint questions. | I53: https://github.com/anshu8830/anshu/blob/main/curriculum/08-skill-checkpoints.md | J53: 2 | K53: P3 (DONE) | L53: ☐
A54: 53 | B54: 46321 | C54: Mon | D54: W5 | E54: P3 | F54: Reading | G54: Embeddings + contrastive learning | H54: Concept note; SBERT sec. 3; DPR sec. 3 (in-batch negatives); InfoNCE (CPC sec. 2.3). | I54: https://github.com/anshu8830/anshu/blob/main/curriculum/concepts/03-retrieval-and-vector-search.md | J54: 1.5 | K54: Paper notes #6 | L54: ☐
A55: 54 | B55: 46321 | C55: Mon | D55: W5 | E55: P3 | F55: Code | G55: InfoNCE + bi-encoder fine-tune | H55: Implement InfoNCE with temperature; fine-tune all-MiniLM-L6-v2 on QA pairs for 1 epoch; MRR before/after. | I55: https://sbert.net/ | J55: 2 | K55: P4: contrastive.py | L55: ☐
A56: 55 | B56: 46322 | C56: Tue | D56: W5 | E56: P3 | F56: Reading | G56: TF-IDF + BM25 | H56: IR book ch. 6 and sec. 11.4.3. | I56: https://nlp.stanford.edu/IR-book/html/htmledition/irbook.html | J56: 1 | L56: ☐
A57: 56 | B57: 46322 | C57: Tue | D57: W5 | E57: P3 | F57: Code | G57: BM25 from scratch | H57: Inverted index, k1/b, IDF variants; compare scores/speed with bm25s on BEIR SciFact. | I57: https://github.com/xhluca/bm25s | J57: 2.5 | K57: P4: bm25.py | L57: ☐
A58: 57 | B58: 46323 | C58: Wed | D58: W5 | E58: P3 | F58: Code | G58: IR metrics | H58: Recall@K, Precision@K, MRR, nDCG@K from scratch with unit tests; BEIR paper sec. 3-5. | I58: https://arxiv.org/abs/2104.08663 | J58: 1 | K58: metrics.py | L58: ☐
A59: 58 | B59: 46323 | C59: Wed | D59: W5 | E59: P13 | F59: Experiment | G59: Reproduction #3 - BEIR baseline | H59: BM25 vs dense (e5/bge-small) vs hybrid RRF on SciFact + NFCorpus; your BM25 nDCG@10 on SciFact should land within ~0.02 of the BEIR table. | I59: https://arxiv.org/abs/2104.08663 | J59: 2.5 | K59: Results table | L59: ☐
A60: 59 | B60: 46324 | C60: Thu | D60: W5 | E60: P3 | F60: Reading | G60: IVF + PQ | H60: Pinecone chapters on vector indexes and PQ; PQ paper sec. II-III. | I60: https://www.pinecone.io/learn/series/faiss/product-quantization/ | J60: 1.5 | L60: ☐
A61: 60 | B61: 46324 | C61: Thu | D61: W5 | E61: P3 | F61: Code | G61: IVF-PQ in NumPy | H61: k-means coarse quantizer + nprobe; PQ with m sub-spaces x 256 centroids; ADC tables; recall@10 vs nprobe and bytes/vector. | I61: https://doi.org/10.1109/TPAMI.2010.57 | J61: 2 | K61: P4: ivfpq.py | L61: ☐
A62: 61 | B62: 46325 | C62: Fri | D62: W5 | E62: P3 | F62: Video | G62: HNSW | H62: James Briggs video, then HNSW paper sec. 3-4 (Algorithms 1-4). | I62: https://www.youtube.com/watch?v=QvKMwLjdK-s | J62: 1.5 | L62: ☐
A63: 62 | B63: 46325 | C63: Fri | D63: W5 | E63: P3 | F63: Code | G63: NSW/HNSW | H63: Single-layer NSW with beam search (efSearch), then hierarchy (optional); compare with FAISS IndexHNSWFlat over M/efSearch. | I63: https://arxiv.org/abs/1603.09320 | J63: 2 | K63: P4: hnsw.py + curves | L63: ☐
A64: 63 | B64: 46326 | C64: Sat | D64: W5 | E64: P3 | F64: Project | G64: Assemble retrieval engine | H64: One interface over BM25, Flat, IVF-PQ, HNSW (yours + FAISS), hybrid RRF, cross-encoder reranker, metadata filters, and one DB backend (pgvector HNSW or Qdrant). | I64: https://www.pinecone.io/learn/series/faiss/ | J64: 3 | K64: P4 package | L64: ☐
A65: 64 | B65: 46326 | C65: Sat | D65: W5 | E65: P3 | F65: Review | G65: Benchmark report | H65: Recall/nDCG/latency/memory table across indexes; notes on pre- vs post-filtering in vector DBs. | I65: https://github.com/anshu8830/anshu/blob/main/curriculum/concepts/03-retrieval-and-vector-search.md | J65: 1 | K65: P4 (DONE) | L65: ☐
A66: 65 | B66: 46328 | C66: Mon | D66: W6 | E66: P4 | F66: Video | G66: RAG foundations | H66: RAG paper sec. 2 (RAG-Sequence vs RAG-Token) + Kiela CS25 lecture. | I66: https://www.youtube.com/watch?v=mE7IDf2SmJg | J66: 1.5 | K66: Paper notes #7 | L66: ☐
A67: 66 | B67: 46328 | C67: Mon | D67: W6 | E67: P4 | F67: Code | G67: Baseline pipeline + golden set v0 | H67: Docling parse -> fixed chunks -> embed -> retrieve (P4) -> numbered sources -> answer with citations. Write 30 real Q/A pairs now. | I67: https://docling-project.github.io/docling/ | J67: 2 | K67: P5 baseline | L67: ☐
A68: 67 | B68: 46329 | C68: Tue | D68: W6 | E68: P4 | F68: Video | G68: Advanced retrieval practice | H68: Clavie talk + Anthropic Contextual Retrieval. | I68: https://www.youtube.com/watch?v=0nA5QG3087g | J68: 1 | L68: ☐
A69: 68 | B69: 46329 | C69: Tue | D69: W6 | E69: P4 | F69: Experiment | G69: Chunking study | H69: Fixed vs recursive vs structure-aware vs semantic; parent-child; contextual headers; metadata filters. Measure recall@5 on golden set. | I69: https://www.anthropic.com/news/contextual-retrieval | J69: 2.5 | K69: Chunking table | L69: ☐
A70: 69 | B70: 46330 | C70: Wed | D70: W6 | E70: P13 | F70: Paper | G70: HyDE + query-side methods | H70: HyDE sec. 3; multi-query, decomposition, conversational rewriting. | I70: https://arxiv.org/abs/2212.10496 | J70: 1 | L70: ☐
A71: 70 | B71: 46330 | C71: Wed | D71: W6 | E71: P4 | F71: Code | G71: Full retrieval chain | H71: Rewrite -> multi-query -> hybrid -> RRF -> cross-encoder rerank -> extractive compression -> generate; ablate each stage. | I71: https://arxiv.org/abs/2212.10496 | J71: 2.5 | K71: P5 chain | L71: ☐
A72: 71 | B72: 46331 | C72: Thu | D72: W6 | E72: P4 | F72: Paper | G72: Lost in the Middle | H72: Sec. 2-4; implement context ordering (best chunks at edges) and token budgets. | I72: https://arxiv.org/abs/2307.03172 | J72: 1 | L72: ☐
A73: 72 | B73: 46331 | C73: Thu | D73: W6 | E73: P4 | F73: Paper | G73: Late interaction | H73: ColBERT sec. 3 (MaxSim); BGE-M3 dense+sparse+multi-vector. | I73: https://arxiv.org/abs/2004.12832 | J73: 1 | L73: ☐
A74: 73 | B74: 46331 | C74: Thu | D74: W6 | E74: P4 | F74: Code | G74: Multi-vector path | H74: BGE-M3 multi-vector or ColBERT-style MaxSim reranker vs cross-encoder: quality vs latency. | I74: https://arxiv.org/abs/2402.03216 | J74: 1.5 | L74: ☐
A75: 74 | B75: 46332 | C75: Fri | D75: W6 | E75: P4 | F75: Paper | G75: Agentic & graph RAG | H75: Self-RAG overview; GraphRAG sec. 2-3; retrieval planning (whether / what / how many hops). | I75: https://arxiv.org/abs/2404.16130 | J75: 1.5 | L75: ☐
A76: 75 | B76: 46332 | C76: Fri | D76: W6 | E76: P4 | F76: Code | G76: Agentic RAG router | H76: Answer-directly / retrieve / decompose router, sufficiency check, max hops; optional entity graph for global questions. | I76: https://arxiv.org/abs/2310.11511 | J76: 2 | K76: router.py | L76: ☐
A77: 76 | B77: 46333 | C77: Sat | D77: W6 | E77: P4 | F77: Project | G77: P5 polish | H77: Config-driven pipeline, span-level citations, abstain when unsupported, caching, streaming FastAPI endpoint. | I77: https://arxiv.org/abs/2005.11401 | J77: 2.5 | K77: P5 service | L77: ☐
A78: 77 | B78: 46333 | C78: Sat | D78: W6 | E78: P4 | F78: Reading | G78: Map P5 onto LangChain + LlamaIndex | H78: Read-only: how LangChain (document loaders, text splitters, retrievers, vector-store integrations) and LlamaIndex (nodes, indices, query engines, rerankers) name the stages you just built. You should recognise every abstraction as something you already wrote. | I78: https://developers.llamaindex.ai/python/framework/ | J78: 0.5 | K78: mapping table | L78: ☐
A79: 78 | B79: 46333 | C79: Sat | D79: W6 | E79: P4 | F79: Review | G79: Ablation table v0 | H79: Retrieval recall@5 + manual answer check per configuration (full metrics next week). | I79: https://github.com/anshu8830/anshu/blob/main/curriculum/concepts/04-rag-and-evaluation-metrics.md | J79: 1 | K79: P5 (DONE) | L79: ☐
A80: 79 | B80: 46335 | C80: Mon | D80: W7 | E80: P5 | F80: Reading | G80: Evals mindset | H80: Husain 'Your AI Product Needs Evals' + first half of the judge guide. | I80: https://hamel.dev/blog/posts/evals/ | J80: 1.5 | L80: ☐
A81: 80 | B81: 46335 | C81: Mon | D81: W7 | E81: P5 | F81: Experiment | G81: Error analysis + golden set v1 | H81: Read 50 P5 traces, open-code failures into a taxonomy; grow the golden set to 100+ (human-written, synthetic-then-verified, unanswerable/adversarial). | I81: https://hamel.dev/blog/posts/evals/ | J81: 2 | K81: taxonomy.md + dataset | L81: ☐
A82: 81 | B82: 46336 | C82: Tue | D82: W7 | E82: P13 | F82: Paper | G82: LLM-as-judge research | H82: MT-Bench sec. 3-4 (biases), G-Eval sec. 2, Yan's survey, Shankar 'Who Validates the Validators'. | I82: https://arxiv.org/abs/2306.05685 | J82: 1.5 | K82: Paper notes #8 | L82: ☐
A83: 82 | B83: 46336 | C83: Tue | D83: W7 | E83: P5 | F83: Code | G83: Judges + calibration | H83: Binary rubric judge, pairwise with position swap, reference-based correctness. Label 60 examples yourself; iterate until judge-human kappa >= 0.6. | I83: https://hamel.dev/blog/posts/llm-judge/ | J83: 2 | K83: judges.py + calibration | L83: ☐
A84: 83 | B84: 46337 | C84: Wed | D84: W7 | E84: P5 | F84: Reading | G84: RAG metric definitions | H84: RAGAS sec. 3 + concept note. | I84: https://arxiv.org/abs/2309.15217 | J84: 1 | L84: ☐
A85: 84 | B85: 46337 | C85: Wed | D85: W7 | E85: P5 | F85: Code | G85: RAG metrics from scratch | H85: Context precision/recall (gold passages), faithfulness (claim extraction -> per-claim support check), answer relevance, citation accuracy; compare with the ragas library. | I85: https://docs.ragas.io/en/stable/concepts/metrics/available_metrics/ | J85: 2.5 | K85: rag_metrics.py | L85: ☐
A86: 85 | B86: 46338 | C86: Thu | D86: W7 | E86: P5 | F86: Video | G86: Benchmarks & contamination | H86: CS336 L12 trace/video; skim the HF Evaluation Guidebook. | I86: https://cs336.stanford.edu/lectures/?trace=lecture_12 | J86: 1 | L86: ☐
A87: 86 | B87: 46338 | C87: Thu | D87: W7 | E87: P5 | F87: Reading | G87: Statistics for evals | H87: Bootstrap CIs, paired tests (paired bootstrap / McNemar), sample sizes; online A/B tests (unit of randomization, guardrails); human-eval protocols and inter-annotator agreement. | I87: https://github.com/anshu8830/anshu/blob/main/curriculum/concepts/04-rag-and-evaluation-metrics.md | J87: 1 | K87: stats.py | L87: ☐
A88: 87 | B88: 46338 | C88: Thu | D88: W7 | E88: P5 | F88: Code | G88: Standard benchmark harnesses | H88: Run lm-evaluation-harness on a small open model (ARC-easy, HellaSwag, GSM8K subset); write one custom Inspect task. | I88: https://inspect.aisi.org.uk/ | J88: 1.5 | L88: ☐
A89: 88 | B89: 46339 | C89: Fri | D89: W7 | E89: P5 | F89: Reading | G89: Agent & tool-call evals | H89: Anthropic agent-evals post; tau-bench sec. 3-4 (pass^k, DB-state checks); tool-selection accuracy, argument AST match, trajectory efficiency. | I89: https://www.anthropic.com/engineering/demystifying-evals-for-ai-agents | J89: 1.5 | L89: ☐
A90: 89 | B90: 46339 | C90: Fri | D90: W7 | E90: P5 | F90: Code | G90: Agent eval schema | H90: Task format, outcome graders (tests pass / state), trajectory graders, cost/latency; write 20 tasks for P8 and the capstone. | I90: https://arxiv.org/abs/2406.12045 | J90: 2 | K90: agent_tasks.jsonl | L90: ☐
A91: 90 | B91: 46340 | C91: Sat | D91: W7 | E91: P5 | F91: Project | G91: Build ragevals | H91: Runners, metrics, calibration report, bootstrap CIs, pytest + GitHub Actions gate that fails on a significant regression, markdown/HTML report. | I91: https://hamel.dev/blog/posts/llm-judge/ | J91: 3 | K91: P6 package | L91: ☐
A92: 91 | B92: 46340 | C92: Sat | D92: W7 | E92: P5 | F92: Review | G92: Re-score P5 ablations | H92: Publish the ablation table with CIs and pick the production config. | I92: https://github.com/anshu8830/anshu/blob/main/curriculum/concepts/04-rag-and-evaluation-metrics.md | J92: 1 | K92: P6 (DONE) | L92: ☐
A93: 92 | B93: 46342 | C93: Mon | D93: W8 | E93: P6 | F93: Video | G93: Post-training landscape | H93: CS336 L15 slides + video; InstructGPT sec. 3.1-3.5; pretraining vs continued pretraining vs instruction tuning. | I93: https://github.com/stanford-cs336/lectures/blob/main/lecture_15.pdf | J93: 1.5 | K93: Paper notes #9 | L93: ☐
A94: 93 | B94: 46342 | C94: Mon | D94: W8 | E94: P6 | F94: Reading | G94: Chat templates | H94: HF LLM course ch. 11 + chat templating docs; inspect the Jinja template of Qwen3 or Llama-3 and its special tokens. | I94: https://huggingface.co/docs/transformers/chat_templating | J94: 2 | L94: ☐
A95: 94 | B95: 46343 | C95: Tue | D95: W8 | E95: P6 | F95: Code | G95: SFT from scratch | H95: SmolLM2-360M or Qwen3-0.6B-Base: chat template, assistant-only masking with -100, packing caveats, eval loss; then replicate with TRL SFTTrainer and compare loss curves. | I95: https://huggingface.co/docs/trl/sft_trainer | J95: 3.5 | K95: P7: sft.py | L95: ☐
A96: 95 | B96: 46344 | C96: Wed | D96: W8 | E96: P6 | F96: Paper | G96: LoRA | H96: LoRA sec. 4 + 'LoRA Without Regret'. | I96: https://arxiv.org/abs/2106.09685 | J96: 1 | L96: ☐
A97: 96 | B97: 46344 | C97: Wed | D97: W8 | E97: P6 | F97: Code | G97: LoRA from scratch | H97: LoRALinear (freeze base, A random, B=0, alpha/r, dropout, merge/unmerge); inject into q,k,v,o + MLP; verify trainable params; compare with PEFT. | I97: https://thinkingmachines.ai/blog/lora/ | J97: 2.5 | K97: P7: lora.py | L97: ☐
A98: 97 | B98: 46345 | C98: Thu | D98: W8 | E98: P6 | F98: Paper | G98: QLoRA + quantization basics | H98: QLoRA sec. 3; first half of the quantization visual guide (absmax, zero-point, block-wise). | I98: https://arxiv.org/abs/2305.14314 | J98: 1 | L98: ☐
A99: 98 | B99: 46345 | C99: Thu | D99: W8 | E99: P6 | F99: Experiment | G99: QLoRA an 8B model | H99: Qwen3-8B or Llama-3.1-8B on one 24 GB GPU via Unsloth (or TRL+PEFT+bitsandbytes). Track VRAM and tokens/s; save adapter; merge for serving. | I99: https://unsloth.ai/docs/get-started/fine-tuning-llms-guide | J99: 2.5 | K99: Adapter | L99: ☐
A100: 99 | B100: 46346 | C100: Fri | D100: W8 | E100: P6 | F100: Reading | G100: Dataset preparation | H100: Task spec, sourcing, synthetic generation with verification, dedup, decontamination vs eval set, chat formatting, splits (smol-course modules). | I100: https://github.com/huggingface/smol-course | J100: 1.5 | L100: ☐
...

Sheet Projects
A1: ID | B1: Project | C1: Weeks | D1: Due | E1: Deliverable | F1: Skills developed | G1: Status | H1: Done | I1: Your repo link / notes
A2: P1 | B2: Attention from scratch | C2: W1 | D2: 46298 | E2: attention.py (SDPA, masks, MHA, cross-attn) + pytest suite + experiment notebook | F2: Q/K/V shapes, masking, sqrt(d_k) scaling, tests against PyTorch reference | G2: Not started | H2: ☐
A3: P2 | B3: Transformer from scratch | C3: W2 | D3: 46305 | E3: Decoder-only GPT (RoPE, RMSNorm, SwiGLU, GQA) + encoder-decoder trained on a toy seq2seq task | F3: Block design, pre-norm residuals, RoPE, GQA, param counting | G3: Not started | H3: ☐
A4: P3 | B4: Tokenizer + small GPT trained end-to-end | C4: W3-W4 | D4: 46319 | E4: Byte-level BPE, training loop, TinyStories model, KV-cache generation, sampling suite, ablation report | F4: BPE, cross-entropy/perplexity, AdamW + schedules, KV cache, sampling, scaling-law fit, MoE layer | G4: Not started | H4: ☐
A5: P4 | B5: Embedding & retrieval engine | C5: W5 | D5: 46326 | E5: BM25, IVF-PQ, HNSW (own + FAISS), hybrid RRF, reranker, pgvector/Qdrant backend, benchmark report | F5: Contrastive learning, sparse vs dense retrieval, ANN algorithms, IR metrics | G5: Not started | H5: ☐
A6: P5 | B6: Advanced RAG system | C6: W6 | D6: 46333 | E6: Config-driven RAG: parsing, chunking variants, query rewriting/HyDE, hybrid+rerank, agentic router, citations | F6: Every RAG stage + its failure modes, ablation discipline | G6: Not started | H6: ☐
A7: P6 | B7: RAG / LLM evaluation framework | C7: W7 | D7: 46340 | E7: ragevals: golden sets, retrieval + judge metrics, judge calibration, bootstrap CIs, CI regression gate | F7: Error analysis, LLM-as-judge, faithfulness, statistics, regression testing | G7: Not started | H7: ☐
A8: P7 | B8: Fine-tune an open LLM (SFT + LoRA/QLoRA + DPO + GRPO) | C8: W8-W9 | D8: 46354 | E8: SFT-from-scratch, LoRA-from-scratch, QLoRA 8B run, DPO run, GRPO run on verifiable math, eval report | F8: Chat templates, loss masking, LoRA/QLoRA, preference optimization, RLVR | G8: Not started | H8: ☐
A9: P8 | B9: AI research agent | C9: W10 | D9: 46361 | E9: Framework-free agent loop -> planning, memory, reflection, HITL; LangGraph port; agent eval on 20 tasks | F9: Tool calling, ReAct, memory, multi-agent, agent security, agent evaluation | G9: Not started | H9: ☐
A10: P9 | B10: Custom MCP server | C10: W10 | D10: 46361 | E10: MCP server over your retrieval engine: tools + resources + prompts, stdio + Streamable HTTP, auth, tests | F10: MCP architecture, transports, auth, tool design | G10: Not started | H10: ☐
A11: P10 | B11: Optimize & serve an LLM with vLLM | C11: W11 | D11: 46368 | E11: Benchmarked vLLM deployment: BF16/FP8/INT4, prefix caching, spec decoding; perf report with roofline math | F11: GPU fundamentals, KV cache, batching, quantization, TTFT/TPOT | G11: Not started | H11: ☐
A12: P11 | B12: Multimodal RAG | C12: W12 | D12: 46375 | E12: PDF/figure/table/audio RAG: Docling + ColPali-style page retrieval + VLM answers with page citations | F12: ViT/CLIP, VLM architecture, document understanding, Whisper | G12: Not started | H12: ☐
A13: CAP | B13: Capstone: AI Software Engineer | C13: W13-W14 | D13: 46387 | E13: Repo-aware coding agent with RAG, MCP, memory, planning, sandboxed execution, routing, HITL, eval on SWE-bench subset | F13: Everything - integration, evaluation and hardening | G13: Not started | H13: ☐

Sheet Papers
A1: # | B1: Title | C1: Authors | D1: Year | E1: Difficulty (1-5) | F1: Week | G1: Link | H1: Why it matters | I1: Prerequisites | J1: Read carefully | K1: Implement | L1: Reproduce | M1: Tier | N1: Read | O1: Notes
A2: 1 | B2: How to Read a Paper | C2: S. Keshav | D2: 2007 | E2: 1 | F2: W1 | G2: http://ccr.sigcomm.org/online/files/p83-keshavA.pdf | H2: The three-pass method you will use for every paper below. | I2: None. | J2: Whole paper (2 pages). | K2: A paper-notes template in your repo. | L2: - | M2: CORE | N2: ☐
A3: 2 | B3: Improving Language Understanding by Generative Pre-Training (GPT-1) | C3: Radford, Narasimhan, Salimans, Sutskever | D3: 2018 | E3: 1 | F3: W2 | G3: https://cdn.openai.com/research-covers/language-unsupervised/language_understanding_paper.pdf | H3: Origin of generative pretraining + fine-tuning. | I3: Attention Is All You Need. | J3: Sections 1, 3.1-3.3. | K3: - | L3: - | M3: CORE | N3: ☐
A4: 3 | B4: GLU Variants Improve Transformer | C4: Shazeer | D4: 2020 | E4: 1 | F4: W2 | G4: https://arxiv.org/abs/2002.05202 | H4: Source of SwiGLU used in Llama/Qwen. | I4: FFN block; gating. | J4: Whole paper (4 pages). | K4: SwiGLU FFN. | L4: - | M4: CORE | N4: ☐
A5: 4 | B5: Neural Machine Translation of Rare Words with Subword Units (BPE) | C5: Sennrich, Haddow, Birch | D5: 2015 | E5: 1 | F5: W3 | G5: https://arxiv.org/abs/1508.07909 | H5: The BPE algorithm behind GPT tokenizers. | I5: None. | J5: Section 3.2 + Algorithm 1. | K5: BPE trainer (P3). | L5: - | M5: CORE | N5: ☐
A6: 5 | B6: SentencePiece | C6: Kudo, Richardson | D6: 2018 | E6: 1 | F6: W3 | G6: https://arxiv.org/abs/1808.06226 | H6: Language-independent tokenization; unigram LM alternative. | I6: BPE paper. | J6: Sections 2-3. | K6: Train BPE vs unigram and compare. | L6: - | M6: CORE | N6: ☐
A7: 6 | B7: Lost in the Middle | C7: Liu, Lin, Hewitt, Paranjape, Bevilacqua, Petroni, Liang | D7: 2023 | E7: 1 | F7: W6 | G7: https://arxiv.org/abs/2307.03172 | H7: Position effects in long contexts - drives context ordering. | I7: RAG basics. | J7: Sections 2-4. | K7: - | L7: Position sweep on your RAG. | M7: CORE | N7: ☐
A8: 7 | B8: Chain-of-Thought Prompting | C8: Wei et al. | D8: 2022 | E8: 1 | F8: W9 | G8: https://arxiv.org/abs/2201.11903 | H8: Reasoning traces as a capability lever. | I8: Prompting. | J8: Sections 2-3. | K8: - | L8: - | M8: CORE | N8: ☐
A9: 8 | B9: Attention Is All You Need | C9: Vaswani, Shazeer, Parmar, Uszkoreit, Jones, Gomez, Kaiser, Polosukhin | D9: 2017 | E9: 2 | F9: W1 | G9: https://arxiv.org/abs/1706.03762 | H9: Defines the architecture everything else modifies. | I9: Matrix multiplication, softmax, residual nets; the W1 attention concept note. | J9: 3.1-3.2.3 (attention + multi-head), 3.5 (positional encoding), Table 3 ablations. | K9: Scaled dot-product attention, MHA, sinusoidal PE (P1/P2). | L9: Table 3 row (A): vary heads at fixed compute on a toy task. | M9: CORE | N9: ☐
A10: 9 | B10: BERT: Pre-training of Deep Bidirectional Transformers | C10: Devlin, Chang, Lee, Toutanova | D10: 2018 | E10: 2 | F10: W2 | G10: https://arxiv.org/abs/1810.04805 | H10: Encoder-only counterpart; explains why bidirectional encoders still dominate embeddings/rerankers. | I10: Transformer encoder; masked vs causal attention. | J10: Sections 3.1-3.2 (MLM, NSP), Figure 1. | K10: Masked-LM objective on your encoder (optional). | L10: - | M10: CORE | N10: ☐
A11: 10 | B11: Language Models are Unsupervised Multitask Learners (GPT-2) | C11: Radford, Wu, Child, Luan, Amodei, Sutskever | D11: 2019 | E11: 2 | F11: W2 | G11: https://cdn.openai.com/better-language-models/language_models_are_unsupervised_multitask_learners.pdf | H11: Zero-shot task transfer from pure LM; byte-level BPE; pre-norm. | I11: GPT-1; byte-level BPE idea. | J11: Sections 2.1-2.3 (data, input representation, model changes). | K11: Byte-level BPE (P3). | L11: - | M11: CORE | N11: ☐
A12: 11 | B12: Root Mean Square Layer Normalization | C12: Zhang, Sennrich | D12: 2019 | E12: 2 | F12: W2 | G12: https://arxiv.org/abs/1910.07467 | H12: Why modern LLMs dropped mean-centering. | I12: LayerNorm forward/backward. | J12: Sections 2-3. | K12: RMSNorm layer + test. | L12: - | M12: CORE | N12: ☐
A13: 12 | B13: Fast Transformer Decoding: One Write-Head is All You Need (MQA) | C13: Shazeer | D13: 2019 | E13: 2 | F13: W2 | G13: https://arxiv.org/abs/1911.02150 | H13: First paper to attack KV-cache bandwidth. | I13: MHA; KV cache (W4 concept note helps). | J13: Sections 2-3. | K13: MQA as GQA special case. | L13: - | M13: CORE | N13: ☐
... A82: 81 | B82: DeepSeek-V3 Technical Report | C82: DeepSeek-AI | D82: 2024 | E82: 4 | F82: 2027 | G82: https://arxiv.org/abs/2412.19437 | H82: MLA, auxiliary-loss-free MoE balancing, FP8 training, MTP - a frontier training systems case study. | I82: MoE, MLA, FP8, pipeline parallelism. | J82: Sections 2-3. | K82: - | L82: - | M82: EXT | N82: ☐

Sheet Resources
A1: Kind | B1: Title | C1: By / channel | D1: Duration | E1: Link | F1: Week(s) | G1: Why / notes
A2: PRIMARY | B2: Understanding Deep Learning (Prince), ch. 5-9 - targeted revision | E2: https://udlbook.github.io/udlbook/ | F2: W1
A3: PRIMARY | B3: CS336 2026 Lecture 2 trace - PyTorch, einops, resource accounting | E3: https://cs336.stanford.edu/lectures/?trace=lecture_02 | F3: W1
A4: PRIMARY | B4: Concept note: attention & transformer shapes | E4: https://github.com/anshu8830/anshu/blob/main/curriculum/concepts/01-attention-and-transformer.md | F4: W1, W2
A5: PRIMARY | B5: The Illustrated Transformer (Alammar) | E5: https://jalammar.github.io/illustrated-transformer/ | F5: W1
A6: SECONDARY | B6: The Matrix Calculus You Need for Deep Learning | E6: https://explained.ai/matrix-calculus/ | F6: W1
A7: SECONDARY | B7: The Annotated Transformer | E7: https://nlp.seas.harvard.edu/annotated-transformer/ | F7: W1, W2
A8: REFERENCE | B8: How to Read a Paper (Keshav) | E8: http://ccr.sigcomm.org/online/files/p83-keshavA.pdf | F8: W1
A9: VIDEO | B9: Building makemore Part 4: Becoming a Backprop Ninja | C9: Andrej Karpathy | D9: 1h55m | E9: https://www.youtube.com/watch?v=q8SA3rM6ckI | F9: W1 | G9: Only if the diagnostic shows you can't write a manual backward pass; the best drill for gradient flow. (P0 backprop)
A10: VIDEO | B10: Transformers, the tech behind LLMs | DL5 | C10: 3Blue1Brown | D10: 27m | E10: https://www.youtube.com/watch?v=wjZofJX0v4M | F10: W1 | G10: Geometric intuition for embeddings and next-token prediction before any equations. (P1 intuition)
A11: VIDEO | B11: Attention in transformers, step-by-step | DL6 | C11: 3Blue1Brown | D11: 26m | E11: https://www.youtube.com/watch?v=eMlx5fFNoYc | F11: W1 | G11: Clearest visual explanation of Q, K, V and why masking exists. (P1 attention)
A12: VIDEO | B12: Let's build GPT (Karpathy) - code along | C12: Andrej Karpathy | D12: 1h56m | E12: https://www.youtube.com/watch?v=kCc8FmEb1nY | F12: W2 | G12: Fastest route from bigram model to a working decoder block; you will diverge from it with modern components. (P1 implementation)
A13: PRIMARY | B13: CS336 2026 Lecture 3 - Architectures & hyperparameters (slides) | E13: https://github.com/stanford-cs336/lectures/blob/main/lecture_03.pdf | F13: W2
A14: SECONDARY | B14: The Big LLM Architecture Comparison (Raschka, updated 2026) | E14: https://magazine.sebastianraschka.com/p/the-big-llm-architecture-comparison | F14: W2
A15: REFERENCE | B15: Build a Large Language Model (From Scratch) code | E15: https://github.com/rasbt/LLMs-from-scratch | F15: W2
A16: VIDEO | B16: Stanford CS336 Spring 2026 - Lecture 3: Architectures | C16: Tatsu Hashimoto (Stanford) | D16: ~1h20m | E16: https://www.youtube.com/watch?v=lVynu4bo1rY | F16: W2 | G16: Evidence-based survey of pre-norm, RMSNorm, SwiGLU, RoPE, GQA and hyperparameter conventions across real LLMs. (P1 architecture)
A17: VIDEO | B17: LLaMA explained: KV-Cache, RoPE, RMS Norm, GQA, SwiGLU | C17: Umar Jamil | D17: ~1h10m | E17: https://www.youtube.com/watch?v=Mn_9W1nCFLo | F17: W2 | G17: Best derivation-level explanation of RoPE and GQA with code. (P1 RoPE/GQA)
A18: PRIMARY | B18: CS336 Assignment 1 (Basics) - handout + tests are the spec | E18: https://github.com/stanford-cs336/assignment1-basics | F18: W3
A19: VIDEO | B19: Let's build the GPT Tokenizer (Karpathy) + minbpe | C19: Andrej Karpathy | D19: 2h13m | E19: https://www.youtube.com/watch?v=zduSFxRajkE | F19: W3 | G19: Explains byte-level BPE, regex pre-tokenization, special tokens and the weird failures tokenization causes. (P2 tokenization)
A20: PRIMARY | B20: Concept note: prompt -> next token (loss, perplexity sections) | E20: https://github.com/anshu8830/anshu/blob/main/curriculum/concepts/02-prompt-to-next-token.md | F20: W3, W4
A21: SECONDARY | B21: minbpe reference implementation | E21: https://github.com/karpathy/minbpe | F21: W3
A22: SECONDARY | B22: nanoGPT reference | E22: https://github.com/karpathy/nanoGPT | F22: W3
A23: REFERENCE | B23: A Recipe for Training Neural Networks (Karpathy) | E23: http://karpathy.github.io/2019/04/25/recipe/ | F23: W3
A24: VIDEO | B24: Stanford CS336 Spring 2026 - Lecture 1: Overview, Tokenization | C24: Percy Liang (Stanford) | D24: ~1h20m | E24: https://www.youtube.com/watch?v=JuoVZkPBiKk | F24: W3 | G24: Frames the whole LM pipeline and the tokenizer design space used in A1. (P2 tokenization)
A25: PRIMARY | B25: CS336 2026 Lecture 10 trace - Inference | E25: https://cs336.stanford.edu/lectures/?trace=lecture_10 | F25: W4
A26: PRIMARY | B26: CS336 2026 Lecture 9 slides - Scaling laws | E26: https://github.com/stanford-cs336/lectures/blob/main/lecture_09.pdf | F26: W4
A27: PRIMARY | B27: CS336 2026 Lecture 4 slides - Attention alternatives & MoE | E27: https://github.com/stanford-cs336/lectures/blob/main/lecture_04.pdf | F27: W4
A28: SECONDARY | B28: Transformer Inference Arithmetic (kipply) | E28: https://kipply.github.io/blog/transformer-inference-arithmetic/ | F28: W4
A29: SECONDARY | B29: A Visual Guide to Mixture of Experts (Grootendorst) | E29: https://newsletter.maartengrootendorst.com/p/a-visual-guide-to-mixture-of-experts | F29: W4
A30: SECONDARY | B30: LLM Visualization (Bycroft) - 3D walk through one token | E30: https://bbycroft.net/llm | F30: W4
A31: VIDEO | B31: CS336 2026 playlist (lectures 4, 9, 10, 11) | C31: Liang / Hashimoto (Stanford) | D31: ~1h20m each | E31: https://www.youtube.com/playlist?list=PLoROMvodv4rMqXOcazWaTUHhq-yembLCV | F31: W4, W7, W8, W9, W12 | G31: Collective communication and DP/TP/PP trade-offs with real numbers. (P11 distributed)
A32: VIDEO | B32: Stanford CS229: Building Large Language Models (LLMs) | C32: Yann Dubois (Stanford) | D32: ~1h44m | E32: https://www.youtube.com/watch?v=9vM4p9NN0Ts | F32: W4 | G32: Optional single-sitting overview tying pretraining, scaling laws, evaluation and post-training together. (P2 overview)
A33: PRIMARY | B33: Concept note: retrieval & vector search | E33: https://github.com/anshu8830/anshu/blob/main/curriculum/concepts/03-retrieval-and-vector-search.md | F33: W5
A34: PRIMARY | B34: Introduction to Information Retrieval - ch. 6 & 11.4.3 (BM25) | E34: https://nlp.stanford.edu/IR-book/html/htmledition/irbook.html | F34: W5
A35: PRIMARY | B35: Faiss: The Missing Manual (Pinecone) - indexes, PQ, HNSW chapters | E35: https://www.pinecone.io/learn/series/faiss/ | F35: W5
A36: SECONDARY | B36: bm25s (fast reference BM25) | E36: https://github.com/xhluca/bm25s | F36: W5
A37: SECONDARY | B37: The Faiss library paper | E37: https://arxiv.org/abs/2401.08281 | F37: W5
A38: REFERENCE | B38: pgvector | E38: https://github.com/pgvector/pgvector | F38: W5
A39: REFERENCE | B39: Qdrant docs | E39: https://qdrant.tech/documentation/ | F39: W5
A40: REFERENCE | B40: Sentence-Transformers docs | E40: https://sbert.net/ | F40: W5
A41: VIDEO | B41: HNSW for Vector Search Explained and Implemented with Faiss | C41: James Briggs | D41: ~35m | E41: https://www.youtube.com/watch?v=QvKMwLjdK-s | F41: W5 | G41: Visual walk-through of the HNSW layers and parameters before you read the paper. (P3 ANN)
A42: PRIMARY | B42: RAG paper (Lewis et al.) | E42: https://arxiv.org/abs/2005.11401 | F42: W6
A43: PRIMARY | B43: Beyond the Basics of RAG (Clavie) - notes page | E43: https://parlance-labs.com/education/rag/ben.html | F43: W6
A44: PRIMARY | B44: Introducing Contextual Retrieval (Anthropic) | E44: https://www.anthropic.com/news/contextual-retrieval | F44: W6
A45: SECONDARY | B45: Docling docs (document parsing) | E45: https://docling-project.github.io/docling/ | F45: W6
A46: SECONDARY | B46: Concept note: RAG & evaluation metrics | E46: https://github.com/anshu8830/anshu/blob/main/curriculum/concepts/04-rag-and-evaluation-metrics.md | F46: W6, W7
A47: REFERENCE | B47: BGE-M3 paper | E47: https://arxiv.org/abs/2402.03216 | F47: W6
A48: REFERENCE | B48: ColBERT paper | E48: https://arxiv.org/abs/2004.12832 | F48: W6
A49: VIDEO | B49: Stanford CS25: V3 - Retrieval Augmented Language Models | C49: Douwe Kiela (Stanford CS25) | D49: 1h19m | E49: https://www.youtube.com/watch?v=mE7IDf2SmJg | F49: W6 | G49: Research-level map of RAG: retriever/generator training, architectures, open problems. (P4 foundations)
A50: VIDEO | B50: Beyond the Basics of Retrieval for Augmenting Generation | C50: Ben Clavie (Answer.AI) | D50: ~1h | E50: https://www.youtube.com/watch?v=0nA5QG3087g | F50: W6 | G50: Practitioner's 'MVP++': BM25 + bi-encoder + reranker + metadata filters, and how to evaluate. (P4 advanced retrieval)
A51: PRIMARY | B51: Your AI Product Needs Evals (Husain) | E51: https://hamel.dev/blog/posts/evals/ | F51: W7
A52: PRIMARY | B52: Using LLM-as-a-Judge: A Complete Guide (Husain) | E52: https://hamel.dev/blog/posts/llm-judge/ | F52: W7
A53: PRIMARY | B53: Demystifying evals for AI agents (Anthropic) | E53: https://www.anthropic.com/engineering/demystifying-evals-for-ai-agents | F53: W7, W13
A54: SECONDARY | B54: Evaluating the Effectiveness of LLM-Evaluators (Eugene Yan) | E54: https://eugeneyan.com/writing/llm-evaluators/ | F54: W7
A55: SECONDARY | B55: LLM Evaluation Guidebook (Hugging Face) | E55: https://huggingface.co/spaces/OpenEvals/evaluation-guidebook | F55: W7
A56: SECONDARY | B56: CS336 2026 Lecture 12 trace - Evaluation | E56: https://cs336.stanford.edu/lectures/?trace=lecture_12 | F56: W7
A57: REFERENCE | B57: Ragas metric definitions | E57: https://docs.ragas.io/en/stable/concepts/metrics/available_metrics/ | F57: W7
A58: REFERENCE | B58: Inspect (UK AISI) eval framework | E58: https://inspect.aisi.org.uk/ | F58: W7
A59: REFERENCE | B59: lm-evaluation-harness | E59: https://github.com/EleutherAI/lm-evaluation-harness | F59: W7
A60: PRIMARY | B60: Hugging Face LLM Course ch. 11 - Supervised fine-tuning | E60: https://huggingface.co/learn/llm-course/chapter11/1 | F60: W8
A61: PRIMARY | B61: CS336 2026 Lecture 15 slides - Mid/post-training (SFT/RLHF) | E61: https://github.com/stanford-cs336/lectures/blob/main/lecture_15.pdf | F61: W8
A62: PRIMARY | B62: LoRA Without Regret (Thinking Machines) | E62: https://thinkingmachines.ai/blog/lora/ | F62: W8
... A77: REFERENCE | B77: CS336 Assignment 5 (GRPO on OLMo-2 1B) - full version deferred to 2027 | E77: https://github.com/stanford-cs336/assignment5-alignment | F77: W9
A78: VIDEO | B78: L3 Policy Gradients and Advantage Estimation (Foundations of Deep RL) | C78: Pieter Abbeel | D78: ~1h | E78: https://www.youtube.com/watch?v=AKbX1Zvo7r8 | F78: W9 | G78: Compact, rigorous policy-gradient derivation; watch L4 (TRPO/PPO) from the same playlist next. (P12 policy gradients)
A79: VIDEO | B79: Reinforcement Learning from Human Feedback explained with math derivations and the PyTorch code | C79: Umar Jamil | D79: ~2h | E79: https://www.youtube.com/watch?v=qGyFrqc34yc | F79: W9 | G79: Walks from policy gradients to PPO-based RLHF with code; watch the PPO + RLHF sections. (P12 RLHF/PPO)
A80: VIDEO | B80: Direct Preference Optimization (DPO) explained: Bradley-Terry model, log probabilities, math | C80: Umar Jamil | D80: ~50m | E80: https://www.youtube.com/watch?v=hvGa5Mba4c8 | F80: W9 | G80: Line-by-line derivation of the DPO loss. (P6 DPO)
A81: PRIMARY | B81: Building effective agents (Anthropic) | E81: https://www.anthropic.com/engineering/building-effective-agents | F81: W10
A82: PRIMARY | B82: Effective context engineering for AI agents (Anthropic) | E82: https://www.anthropic.com/engineering/effective-context-engineering-for-ai-agents | F82: W10, W13
A83: PRIMARY | B83: MCP specification 2026-07-28 (current) | E83: https://modelcontextprotocol.io/specification/2026-07-28 | F83: W10
A84: PRIMARY | B84: MCP 2026-07-28 release notes (what changed: stateless core, deprecations) | E84: https://blog.modelcontextprotocol.io/posts/2026-07-28/ | F84: W10
A85: SECONDARY | B85: Writing effective tools for agents (Anthropic) | E85: https://www.anthropic.com/engineering/writing-tools-for-agents | F85: W10
A86: SECONDARY | B86: How we built our multi-agent research system (Anthropic) | E86: https://www.anthropic.com/engineering/multi-agent-research-system | F86: W10
A87: SECONDARY | B87: LLM Powered Autonomous Agents (Weng) | E87: https://lilianweng.github.io/posts/2023-06-23-agent/ | F87: W10
A88: SECONDARY | B88: LangChain Academy - Introduction to LangGraph (free) | E88: https://academy.langchain.com/courses/intro-to-langgraph | F88: W10
A89: SECONDARY | B89: Hugging Face MCP Course | E89: https://huggingface.co/learn/mcp-course/en/unit0/introduction | F89: W10
A90: SECONDARY | B90: Hugging Face Agents Course | E90: https://huggingface.co/learn/agents-course/en/unit0/introduction | F90: W10
A91: REFERENCE | B91: LangGraph docs | E91: https://docs.langchain.com/oss/python/langgraph/overview | F91: W10
A92: REFERENCE | B92: LangChain middleware docs | E92: https://docs.langchain.com/oss/python/langchain/middleware/overview | F92: W10
... A101: REFERENCE | B101: mini-swe-agent (100-line reference agent) | E101: https://github.com/SWE-agent/mini-swe-agent | F101: W10, W13
A102: VIDEO | B102: How We Build Effective Agents | C102: Barry Zhang (Anthropic) - AI Engineer Summit | D102: ~15m | E102: https://www.youtube.com/watch?v=D7_ipDqhtwk | F102: W10 | G102: Three principles: don't build agents for everything, keep them simple, think like your agent. (P7 design)
A103: PRIMARY | B103: Modal GPU Glossary | E103: https://modal.com/gpu-glossary | F103: W11
A104: PRIMARY | B104: How to Scale Your Model - All About Rooflines (Google DeepMind) | E104: https://jax-ml.github.io/scaling-book/roofline/ | F104: W11
A105: PRIMARY | B105: Making Deep Learning Go Brrrr (Horace He) | E105: https://horace.io/brrr_intro.html | F105: W11
A106: PRIMARY | B106: Inside vLLM: Anatomy of a High-Throughput Inference System (Gordic) | E106: https://www.aleksagordic.com/blog/vllm | F106: W11
A107: PRIMARY | B107: Concept note: GPU & inference math | E107: https://github.com/anshu8830/anshu/blob/main/curriculum/concepts/06-gpu-and-inference-math.md | F107: W11
A108: SECONDARY | B108: CS336 2026 Lecture 5 slides - GPUs/TPUs | E108: https://github.com/stanford-cs336/lectures/blob/main/lecture_05.pdf | F108: W11
A109: SECONDARY | B109: CS336 2026 Lecture 6 trace - Kernels, Triton | E109: https://cs336.stanford.edu/lectures/?trace=lecture_06 | F109: W11
A110: SECONDARY | B110: Triton tutorials | E110: https://triton-lang.org/main/getting-started/tutorials/ | F110: W11
A111: REFERENCE | B111: vLLM docs - automatic prefix caching | E111: https://docs.vllm.ai/en/stable/design/prefix_caching/ | F111: W11
A112: REFERENCE | B112: TensorRT-LLM docs | E112: https://nvidia.github.io/TensorRT-LLM/ | F112: W11
A113: REFERENCE | B113: GPU MODE lectures (code + slides) | E113: https://github.com/gpu-mode/lectures | F113: W11
A114: VIDEO | B114: FlashAttention - Tri Dao | Stanford MLSys #67 | C114: Tri Dao (Stanford MLSys Seminar) | D114: ~1h | E114: https://www.youtube.com/watch?v=gMOAud7hZg4 | F114: W11 | G114: The author explains IO-awareness, tiling and recomputation. (P9 FlashAttention)
A115: VIDEO | B115: Fast LLM Serving with vLLM and PagedAttention | C115: vLLM authors (Woosuk Kwon, Zhuohan Li) | D115: ~30-40m | E115: https://www.youtube.com/watch?v=Oq2SN7uutbQ | F115: W11 | G115: Why KV-cache fragmentation limits batch size and how paging fixes it. (P9 serving)
A116: VIDEO | B116: Speculative Decoding: When Two LLMs are Faster than One | C116: Efficient NLP | D116: ~12m | E116: https://www.youtube.com/watch?v=S-8yr_RibJ4 | F116: W11 | G116: Short, precise explanation of the acceptance rule. (P9 speculative decoding)
A117: VIDEO | B117: Flash Attention derived and coded from first principles with Triton (Python) | C117: Umar Jamil | D117: ~7h | E117: https://www.youtube.com/watch?v=zy8ChVd_oTM | F117: W11 | G117: Optional deep dive (2027 track): derive and write FA in Triton, incl. backward pass. (P9 kernels (stretch))
A118: PRIMARY | B118: The Ultra-Scale Playbook (Hugging Face) | E118: https://huggingface.co/spaces/nanotron/ultrascale-playbook | F118: W12
A119: PRIMARY | B119: Understanding Multimodal LLMs (Raschka) | E119: https://magazine.sebastianraschka.com/p/understanding-multimodal-llms | F119: W12
A120: PRIMARY | B120: Vision Language Models (Better, faster, stronger) - HF 2025 | E120: https://huggingface.co/blog/vlms-2025 | F120: W12
A121: PRIMARY | B121: nanoVLM (repo + blog) | E121: https://github.com/huggingface/nanoVLM | F121: W12
A122: SECONDARY | B122: CS336 2026 Lecture 7 trace + Lecture 8 slides - Parallelism | E122: https://cs336.stanford.edu/lectures/?trace=lecture_07 | F122: W12
...
